LICENSE
README.md
setup.py
dreamer.egg-info/PKG-INFO
dreamer.egg-info/SOURCES.txt
dreamer.egg-info/dependency_links.txt
dreamer.egg-info/requires.txt
dreamer.egg-info/top_level.txt
dreamerv3/__init__.py
dreamerv3/agent.py
dreamerv3/main.py
dreamerv3/rssm.py
embodied/__init__.py
embodied/core/__init__.py
embodied/core/base.py
embodied/core/chunk.py
embodied/core/clock.py
embodied/core/driver.py
embodied/core/limiters.py
embodied/core/random.py
embodied/core/replay.py
embodied/core/selectors.py
embodied/core/streams.py
embodied/core/wrappers.py
embodied/jax/__init__.py
embodied/jax/agent.py
embodied/jax/heads.py
embodied/jax/internal.py
embodied/jax/nets.py
embodied/jax/opt.py
embodied/jax/outs.py
embodied/jax/transform.py
embodied/jax/utils.py
embodied/run/__init__.py
embodied/run/eval_only.py
embodied/run/parallel.py
embodied/run/train.py
embodied/run/train_eval.py