Metadata-Version: 2.1
Name: dreamer
Version: 3.3.1
Summary: Mastering Diverse Domains through World Models
Home-page: http://github.com/danijar/dreamerv3
Author: Danijar Hafner
Author-email: mail@danijar.com
Classifier: Intended Audience :: Science/Research
Classifier: License :: OSI Approved :: MIT License
Classifier: Programming Language :: Python :: 3
Classifier: Topic :: Scientific/Engineering :: Artificial Intelligence
License-File: LICENSE
